asw_mathers/__init__.py
asw_mathers/circle.py
asw_mathers/types.py
asw_mathers/util.py
asw_mathers/version.py
asw_mathers-0.1.7.dist-info/licenses/LICENSE
asw_mathers-0.1.7.dist-info/METADATA
asw_mathers-0.1.7.dist-info/WHEEL
asw_mathers-0.1.7.dist-info/top_level.txt
asw_mathers-0.1.7.dist-info/RECORD
