Metadata-Version: 2.4
Name: asw-mathers
Version: 0.1.7
Summary: A simple math helper library
Author-email: Ahmed <your_email@example.com>
License: 
Requires-Python: >=3.8
License-File: LICENSE
Dynamic: license-file
